priceforecast/__init__.py
priceforecast/__main__.py
priceforecast/cli.py
priceforecast/logs.py
priceforecast/models/__init__.py
priceforecast/models/base.py
priceforecast/models/naive.py
priceforecast/models/nn/__init__.py
priceforecast/models/nn/base_nn.py
priceforecast/models/nn/config.py
priceforecast/models/nn/data_preparation.py
priceforecast/models/nn/simple.py
priceforecast/models/nn/transformer.py
priceforecast/models/nn/validation.py
priceforecast/models/registry.py
priceforecast/models/util.py
priceforecast/workflow.py
amiris_priceforecast-2.0.0.dist-info/entry_points.txt
amiris_priceforecast-2.0.0.dist-info/LICENSE
amiris_priceforecast-2.0.0.dist-info/METADATA
amiris_priceforecast-2.0.0.dist-info/WHEEL
amiris_priceforecast-2.0.0.dist-info/RECORD
