Metadata-Version: 2.3
Name: amiris-priceforecast
Version: 2.0.0
Summary: An extension to the agent-based electricity market model AMIRIS providing external electricity price forecasts to the PriceForecasterApi agent
License: Apache-2.0
Keywords: AMIRIS,agent-based modelling,electricity market,electricity price forecast,simulation
Author: Felix Nitsch
Author-email: amiris@dlr.de
Maintainer: Felix Nitsch
Maintainer-email: amiris@dlr.de
Requires-Python: >=3.9,<4.0
Classifier: Development Status :: 5 - Production/Stable
Classifier: Environment :: Console
Classifier: Intended Audience :: Science/Research
Classifier: License :: OSI Approved :: Apache Software License
Classifier: Operating System :: OS Independent
Classifier: Programming Language :: Python :: 3
Classifier: Programming Language :: Python :: 3.9
Classifier: Programming Language :: Python :: 3.10
Classifier: Programming Language :: Python :: 3.11
Classifier: Programming Language :: Python :: 3.12
Classifier: Programming Language :: Python :: 3.13
Classifier: Topic :: Scientific/Engineering
Requires-Dist: darts (>=0.33)
Requires-Dist: fameio (>=3.0)
Requires-Dist: fastapi[all]
Requires-Dist: pandas (>=2.0,<3.0)
Requires-Dist: uvicorn
Project-URL: Homepage, https://helmholtz.software/software/amiris
Project-URL: Repository, https://gitlab.com/dlr-ve/esy/amiris/extensions/priceforecast/
